humantask/__init__.py
humantask/humantask.py
humantask-1.3.6.dist-info/METADATA
humantask-1.3.6.dist-info/WHEEL
humantask-1.3.6.dist-info/RECORD
